inputconditioner.v
//------------------------------------------------------------------------
// Input Conditioner
//    1) Synchronizes input to clock domain
//    2) Debounces input
//    3) Creates pulses at edge transitions
//------------------------------------------------------------------------

module inputconditioner
(
input 	    clk,            // Clock domain to synchronize input to
input	    noisysignal,    // (Potentially) noisy input signal
output reg  conditioned,    // Conditioned output signal
output reg  positiveedge,   // 1 clk pulse at rising edge of conditioned
output reg  negativeedge    // 1 clk pulse at falling edge of conditioned
);

    parameter counterwidth = 3; // Counter size, in bits, >= log2(waittime)
    parameter waittime = 3;     // Debounce delay, in clock cycles
    
    reg[counterwidth-1:0] counter = 0;
    reg synchronizer0 = 0;
    reg synchronizer1 = 0;


    always @(posedge conditioned) positiveedge <=1;
    always @(negedge conditioned) negativeedge <=1;
    
    always @(posedge clk ) begin
        if(conditioned == synchronizer1) begin
            counter <= 0;
            positiveedge = 0;
            negativeedge = 0;
        end
        else begin
            if( counter == waittime) begin
                counter <= 0;
                conditioned <= synchronizer1;
            end
            else begin
                counter <= counter+1;
                positiveedge = 0;
                negativeedge = 0;
            end
        end
        synchronizer0 <= noisysignal;
        synchronizer1 <= synchronizer0;
    end
endmodule

inputconditioner.t.v
//------------------------------------------------------------------------
// Input Conditioner test bench
//------------------------------------------------------------------------
`include "inputconditioner.v"

module testConditioner();

    reg clk;
    reg pin;
    wire conditioned;
    wire rising;
    wire falling;
    
    inputconditioner dut(.clk(clk),
    			 .noisysignal(pin),
			 .conditioned(conditioned),
			 .positiveedge(rising),
			 .negativeedge(falling));


    // Generate clock (50MHz)
    initial clk=0;
    always #10 clk=!clk;    // 50MHz Clock
    
    initial begin
        $dumpfile("input_conditioner.vcd");
        $dumpvars();
    // Your Test Code
    // Be sure to test each of the three conditioner functions:
    // Synchronization, Debouncing, Edge Detection

    //Test 1 - Synchronization
    //Does it actually take five and a half clock cycles (20 units of time each) to get to the output
        pin=0; #80
        if((conditioned !== 0)) begin
            $display("Test Case 1a Failed: %b", conditioned);
        end
        pin=1; #120
        if((conditioned !== 1)) begin 
            $display("Test Case 1b Failed: %b", conditioned);
        end
        pin=0; #100
        if((conditioned !== 1)) begin
            $display("Test Case 1c Failed: %b", conditioned);
        end
        #20
        if((conditioned !== 0)) begin
            $display("Test Case 1d Failed: %b", conditioned);
        end
        pin=1; #100
        if((conditioned !== 0)) begin 
            $display("Test Case 1e Failed: %b", conditioned);
        end
        #20
        if((conditioned !== 1)) begin
            $display("Test Case 1f Failed: %b", conditioned);
        end

    //Test 2 - Debouncing
    //Does the output hold when there is a very noisy input signal
        pin=0; #120
        if((conditioned !== 0)) begin
            $display("Test Case 2a Failed: %b", conditioned);
        end
        pin=1; #10
        pin=0; #10
        pin=1; #10
        pin=0; #10
        pin=1; #10
        pin=0; #10
        pin=1; #10
        pin=0; #10
        pin=1; #10
        pin=0; #10
        pin=1; #10
        pin=0; #10
        pin=1; #10
        pin=0; #10
        if((conditioned !== 0)) begin
            $display("Test Case 2b Failed: %b", conditioned);
        end
        pin=1; #120
        if((conditioned !== 1)) begin
            $display("Test Case 2c Failed: %b", conditioned);
        end
        pin=0; #10
        pin=1; #10
        pin=0; #10
        pin=1; #10
        pin=0; #10
        pin=1; #10
        pin=0; #10
        pin=1; #10
        pin=0; #10
        pin=1; #10
        pin=0; #10
        pin=1; #10
        pin=0; #10
        pin=1; #10
        if((conditioned !== 1)) begin
            $display("Test Case 2d Failed: %b", conditioned);
        end
        pin=0; #120
        if((conditioned !== 0)) begin
            $display("Test Case 2e Failed: %b", conditioned);
        end

    //Test 3 - Edge Detection
    //Does the positive edge and negative edge go high when needed
        pin=1; #120
        if((conditioned !== 1)) begin
            $display("Test Case 3a Failed: %b", conditioned);
        end
        if((rising !== 1) && (falling !== 0)) begin
            $display("Test Case 3b Failed: %b, %b", rising, falling);
        end
        #20
        if((rising !== 0) && (falling !== 0)) begin
            $display("Test Case 3c Failed: %b, %b", rising, falling);
        end

        pin=0; #120
        if((conditioned !== 0)) begin
            $display("Test Case 3d Failed: %b", conditioned);
        end
        if((rising !== 0) && (falling !== 1)) begin
            $display("Test Case 3e Failed: %b, %b", rising, falling);
        end
        #20
        if((rising !== 0) && (falling !== 0)) begin
            $display("Test Case 3f Failed: %b, %b", rising, falling);
        end





    $display("Testing Done");
    end
endmodule

input_conditioner.vcd
$date
	Tue Oct 16 18:52:25 2018
$end
$version
	Icarus Verilog
$end
$timescale
	1s
$end
$scope module testConditioner $end
$var wire 1 ! rising $end
$var wire 1 " falling $end
$var wire 1 # conditioned $end
$var reg 1 $ clk $end
$var reg 1 % pin $end
$scope module dut $end
$var wire 1 $ clk $end
$var wire 1 % noisysignal $end
$var reg 1 # conditioned $end
$var reg 3 & counter [2:0] $end
$var reg 1 " negativeedge $end
$var reg 1 ! positiveedge $end
$var reg 1 ' synchronizer0 $end
$var reg 1 ( synchronizer1 $end
$upscope $end
$upscope $end
$enddefinitions $end
#0
$dumpvars
0(
0'
b0 &
0%
0$
x#
x"
x!
$end
#10
0"
0!
b1 &
1$
#20
0$
#30
b10 &
1$
#40
0$
#50
b11 &
1$
#60
0$
#70
1!
0#
b0 &
1$
#80
0$
1%
#90
1'
0!
1$
#100
0$
#110
1(
1$
#120
0$
#130
b1 &
1$
#140
0$
#150
b10 &
1$
#160
0$
#170
b11 &
1$
#180
0$
#190
1!
1#
b0 &
1$
#200
0$
0%
#210
0'
0!
1$
#220
0$
#230
0(
1$
#240
0$
#250
b1 &
1$
#260
0$
#270
b10 &
1$
#280
0$
#290
b11 &
1$
#300
0$
#310
1"
0#
b0 &
1$
#320
0$
1%
#330
1'
0"
1$
#340
0$
#350
1(
1$
#360
0$
#370
b1 &
1$
#380
0$
#390
b10 &
1$
#400
0$
#410
b11 &
1$
#420
0$
#430
1!
1#
b0 &
1$
#440
0$
0%
#450
0'
0!
1$
#460
0$
#470
0(
1$
#480
0$
#490
b1 &
1$
#500
0$
#510
b10 &
1$
#520
0$
#530
b11 &
1$
#540
0$
#550
1"
0#
b0 &
1$
#560
0$
1%
#570
0"
1$
0%
#580
0$
1%
#590
1$
0%
#600
0$
1%
#610
1$
0%
#620
0$
1%
#630
1$
0%
#640
0$
1%
#650
1$
0%
#660
0$
1%
#670
1$
0%
#680
0$
1%
#690
1$
0%
#700
0$
1%
#710
1'
1$
#720
0$
#730
1(
1$
#740
0$
#750
b1 &
1$
#760
0$
#770
b10 &
1$
#780
0$
#790
b11 &
1$
#800
0$
#810
1!
1#
b0 &
1$
#820
0$
0%
#830
0!
1$
1%
#840
0$
0%
#850
1$
1%
#860
0$
0%
#870
1$
1%
#880
0$
0%
#890
1$
1%
#900
0$
0%
#910
1$
1%
#920
0$
0%
#930
1$
1%
#940
0$
0%
#950
1$
1%
#960
0$
0%
#970
0'
1$
#980
0$
#990
0(
1$
#1000
0$
#1010
b1 &
1$
#1020
0$
#1030
b10 &
1$
#1040
0$
#1050
b11 &
1$
#1060
0$
#1070
1"
0#
b0 &
1$
#1080
0$
1%
#1090
1'
0"
1$
#1100
0$
#1110
1(
1$
#1120
0$
#1130
b1 &
1$
#1140
0$
#1150
b10 &
1$
#1160
0$
#1170
b11 &
1$
#1180
0$
#1190
1!
1#
b0 &
1$
#1200
0$
#1210
0!
1$
#1220
0$
0%
#1230
0'
1$
#1240
0$
#1250
0(
1$
#1260
0$
#1270
b1 &
1$
#1280
0$
#1290
b10 &
1$
#1300
0$
#1310
b11 &
1$
#1320
0$
#1330
1"
0#
b0 &
1$
#1340
0$
#1350
0"
1$
